convren/__init__.py
convren/renamer.py
imgconvren-0.0.2.dist-info/LICENSE
imgconvren-0.0.2.dist-info/METADATA
imgconvren-0.0.2.dist-info/WHEEL
imgconvren-0.0.2.dist-info/top_level.txt
imgconvren-0.0.2.dist-info/RECORD
